pywlgk/__init__.py
pywlgk/utils.py
pywlgk/wlk.py
tests/__init__.py
tests/test_wlk.py
tests/utils.py
PyWLGK-1.0.1.dist-info/LICENSE
PyWLGK-1.0.1.dist-info/METADATA
PyWLGK-1.0.1.dist-info/WHEEL
PyWLGK-1.0.1.dist-info/top_level.txt
PyWLGK-1.0.1.dist-info/RECORD
