Metadata-Version: 2.1
Name: PyWLGK
Version: 1.0.1
Summary: Python package computing Weisfeiler-Lehman graph kernels
Author: Roman Joeres
Maintainer: Roman Joeres
License: MIT
Keywords: bioinformatics,computer-science,graph-kernels,machine-learning,python,wlgk,weisfeiler-lehman-graph-kernel
Classifier: Development Status :: 4 - Beta
Classifier: Programming Language :: Python :: 3.8
Classifier: Programming Language :: Python :: 3.9
Classifier: Programming Language :: Python :: 3.10
Classifier: Programming Language :: Python :: 3.11
Classifier: Programming Language :: Python :: 3.12
Classifier: Intended Audience :: Science/Research
Classifier: Natural Language :: English
Classifier: Topic :: Scientific/Engineering
Requires-Python: >=3.8, <4.0.0
License-File: LICENSE
